pyroll/sander_spreading.py
pyroll_sander_spreading-3.0.0.dist-info/METADATA
pyroll_sander_spreading-3.0.0.dist-info/WHEEL
pyroll_sander_spreading-3.0.0.dist-info/licenses/LICENSE
pyroll_sander_spreading-3.0.0.dist-info/RECORD
